nd_math/__init__.py
nd_math-0.1.1.dist-info/WHEEL
nd_math-0.1.1.dist-info/METADATA
nd_math-0.1.1.dist-info/RECORD
